skillv1/client/__init__.py
skillv1/client/skill_api_datasource.py
skillv1/client/skill_api_skill.py
skillv1/client/skill_api_skill_test.py
skillv1/client/skill_client.py
skillv1/tools/__init__.py
skillv1/tools/skill_edge_synchronizer.py
skillv1/tools/skill_edge_synchronizer_test.py
skillv1/tools/skill_synchronizer.py
skillv1/tools/skill_synchronizer_test.py
skillv1/tools/sync_skill.py
skillv1/tools/sync_skill_test.py
yjskill-1.0.1.7.dist-info/METADATA
yjskill-1.0.1.7.dist-info/WHEEL
yjskill-1.0.1.7.dist-info/top_level.txt
yjskill-1.0.1.7.dist-info/RECORD
