Metadata-Version: 2.1
Name: yjskill
Version: 1.0.1.7
Summary: sdk in python for skill
Home-page: http://www.ai.com
Author: 
Author-email: 
License: MIT
Classifier: Programming Language :: Python
Classifier: Programming Language :: Python :: 3
Classifier: Programming Language :: Python :: 3.7
Classifier: Programming Language :: Python :: 3.8
Classifier: Programming Language :: Python :: 3.9
Requires-Python: >=3.9
Requires-Dist: bce-python-sdk==0.8.87
Requires-Dist: bce-internal-sdk
Requires-Dist: bcelogger
Requires-Dist: windmill-device
Requires-Dist: pydantic>=2.10
Requires-Dist: jobv1
Requires-Dist: windmill-artifact
